extend_vcc/__init__.py
extend_vcc/async_client.py
extend_vcc/auth.py
extend_vcc/base.py
extend_vcc/client.py
extend_vcc/pagination.py
extend_vcc/types.py
extend_vcc/virtual_card.py
extend_vcc/cognito/__init__.py
extend_vcc/cognito/auth.py
extend_vcc/cognito/cognito.py
extend_vcc/cognito/device.py
extend_vcc/cognito/srp.py
extend_vcc/cognito/user.py
extend_vcc-0.1.6.dist-info/LICENSE
extend_vcc-0.1.6.dist-info/METADATA
extend_vcc-0.1.6.dist-info/WHEEL
extend_vcc-0.1.6.dist-info/top_level.txt
extend_vcc-0.1.6.dist-info/RECORD
