Metadata-Version: 2.1
Name: extend-vcc
Version: 0.1.6
Summary: Manage virtual cards on Extend
Home-page: https://github.com/christianobora/extend-vcc
Author: Christian Obora
Author-email: christianobora@uchicago.edu
Requires-Python: >=3.8
License-File: LICENSE
Requires-Dist: requests>=2.26.0
Requires-Dist: requests-toolbelt>=1.0.0
Provides-Extra: dev
Requires-Dist: pytest>=8.3.4; extra == "dev"
Requires-Dist: pytest-cov>=7.0.0; extra == "dev"
Requires-Dist: pytest-asyncio>=0.16.0; extra == "dev"
Requires-Dist: mypy>=1.0.0; extra == "dev"
Requires-Dist: black>=24.10.0; extra == "dev"
Requires-Dist: flake8>=7.1.1; extra == "dev"
Provides-Extra: examples
